{"Id":{"Id":"9732ab35-6469-49e8-908a-6da5624224ab","ModuleId":"(slc)servicemanagement"},"SectionDefinitionLinks":[{"SectionDefinitionID":{"Id":"a4e2826c-f334-4b1e-9704-162c6fd5f2ec","ModuleId":"(slc)servicemanagement"},"IsSoftDeleted":false,"IsOptional":false,"AllowMultipleSections":false}],"Name":"Service Specification Configuration Value","VisualStructure":{"SectionDefinitionInfos":[],"IsHidden":false},"BehaviorDefinitionId":null,"ModuleSettingsOverrides":{"NameDefinition":null,"ScriptSettings":null,"HistorySettings":null},"SyncLastModified":"2025-05-27T14:43:11.7032349Z","LastModifiedBy":"JonasK","CreatedAt":"2025-05-27T14:37:51.8544423Z","CreatedBy":"JonasK"}