{"Id":{"Id":"aa627d77-d73e-4657-8d26-0970371acb9e","ModuleId":"(slc)servicemanagement"},"SectionDefinitionLinks":[{"SectionDefinitionID":{"Id":"8a0d1812-2749-48b9-b673-3bc35c660976","ModuleId":"(slc)servicemanagement"},"IsSoftDeleted":false,"IsOptional":false,"AllowMultipleSections":false}],"Name":"Service Category","VisualStructure":{"SectionDefinitionInfos":[],"IsHidden":false},"BehaviorDefinitionId":null,"ModuleSettingsOverrides":{"NameDefinition":{"ConcatenationItems":[{"$type":"Skyline.DataMiner.Net.Apps.DataMinerObjectModel.Concatenation.FieldValueConcatenationItem, SLNetTypes","FieldDescriptorId":{"Id":"797eeb46-c5fa-4461-aa30-5c83f0a997ee"}}]},"ScriptSettings":null,"HistorySettings":null},"SyncLastModified":"2025-05-26T12:11:49.0408714Z","LastModifiedBy":"Admin","CreatedAt":"2025-05-26T12:11:49.0408714Z","CreatedBy":"Admin"}