{"Id":{"Id":"1fb7b93f-cc9d-46c0-b329-114991f54744","ModuleId":"(slc)configurations"},"SectionDefinitionLinks":[{"SectionDefinitionID":{"Id":"16f36d1f-a19e-4c77-bfd4-2c33a723d57f","ModuleId":"(slc)configurations"},"IsSoftDeleted":false,"IsOptional":false,"AllowMultipleSections":false}],"Name":"Discrete Values","VisualStructure":{"SectionDefinitionInfos":[],"IsHidden":false},"BehaviorDefinitionId":null,"ModuleSettingsOverrides":{"NameDefinition":{"ConcatenationItems":[{"$type":"Skyline.DataMiner.Net.Apps.DataMinerObjectModel.Concatenation.FieldValueConcatenationItem, SLNetTypes","FieldDescriptorId":{"Id":"10be0fab-9224-45b6-9a6c-84e801ed2703"}}]},"ScriptSettings":null,"HistorySettings":null},"SyncLastModified":"2025-05-28T06:22:30.3177496Z","LastModifiedBy":"JonasK","CreatedAt":"2025-05-27T13:57:20.265798Z","CreatedBy":"JonasK"}