{
  "$type": "Skyline.DataMiner.Net.Sections.CustomSectionDefinition, SLNetTypes",
  "FieldDescriptors": {
    "$type": "System.Collections.Generic.List`1[[Skyline.DataMiner.Net.Sections.FieldDescriptor, SLNetTypes]], mscorlib",
    "$values": [
      {
        "$type": "Skyline.DataMiner.Net.Sections.DomInstanceFieldDescriptor, SLNetTypes",
        "DefaultValue": null,
        "DomDefinitionIds": {
          "$type": "System.Collections.Generic.List`1[[Skyline.DataMiner.Net.Apps.DataMinerObjectModel.DomDefinitionId, SLNetTypes]], mscorlib",
          "$values": [
            {
              "$type": "Skyline.DataMiner.Net.Apps.DataMinerObjectModel.DomDefinitionId, SLNetTypes",
              "Id": "0939b425-d30c-4839-9b19-180668beafc1",
              "ModuleId": "(slc)configurations"
            }
          ]
        },
        "FieldType": "System.Guid, mscorlib, Version=4.0.0.0, Culture=neutral, PublicKeyToken=b77a5c561934e089",
        "ID": {
          "$type": "Skyline.DataMiner.Net.Sections.FieldDescriptorID, SLNetTypes",
          "Id": "16babe47-3283-41de-9173-fb55cdbd2528"
        },
        "IsHidden": false,
        "IsOptional": true,
        "IsReadonly": false,
        "IsSoftDeleted": false,
        "ModuleId": "(slc)configurations",
        "Name": "Profile Definition",
        "Tooltip": "Reference to the stored profile definition in (slc)configurations",
        "Validators": {
          "$type": "System.Collections.Generic.List`1[[Skyline.DataMiner.Net.Sections.IFieldValidator, SLNetTypes]], mscorlib",
          "$values": []
        }
      },
      {
        "$type": "Skyline.DataMiner.Net.Sections.DomInstanceFieldDescriptor, SLNetTypes",
        "DefaultValue": null,
        "DomDefinitionIds": {
          "$type": "System.Collections.Generic.List`1[[Skyline.DataMiner.Net.Apps.DataMinerObjectModel.DomDefinitionId, SLNetTypes]], mscorlib",
          "$values": [
            {
              "$type": "Skyline.DataMiner.Net.Apps.DataMinerObjectModel.DomDefinitionId, SLNetTypes",
              "Id": "d5f65610-26b4-4fe0-ab8b-d4a6088711a5",
              "ModuleId": "(slc)configurations"
            }
          ]
        },
        "FieldType": "System.Guid, mscorlib, Version=4.0.0.0, Culture=neutral, PublicKeyToken=b77a5c561934e089",
        "ID": {
          "$type": "Skyline.DataMiner.Net.Sections.FieldDescriptorID, SLNetTypes",
          "Id": "a163544f-d48a-42fe-916e-5f41a9f3d15e"
        },
        "IsHidden": false,
        "IsOptional": true,
        "IsReadonly": false,
        "IsSoftDeleted": false,
        "ModuleId": "(slc)configurations",
        "Name": "Profile",
        "Tooltip": "Reference to the stored profile in (slc)configurations",
        "Validators": {
          "$type": "System.Collections.Generic.List`1[[Skyline.DataMiner.Net.Sections.IFieldValidator, SLNetTypes]], mscorlib",
          "$values": []
        }
      },
      {
        "$type": "Skyline.DataMiner.Net.Sections.FieldDescriptor, SLNetTypes",
        "DefaultValue": null,
        "FieldType": "System.Boolean, mscorlib, Version=4.0.0.0, Culture=neutral, PublicKeyToken=b77a5c561934e089",
        "ID": {
          "$type": "Skyline.DataMiner.Net.Sections.FieldDescriptorID, SLNetTypes",
          "Id": "db86889b-7a2a-4c7f-b617-7b6f9334f850"
        },
        "IsHidden": false,
        "IsOptional": true,
        "IsReadonly": false,
        "IsSoftDeleted": false,
        "Name": "Mandatory at Service Level",
        "Tooltip": "Defines if mandatory to fill this parameter with a value at Service Level",
        "Validators": {
          "$type": "System.Collections.Generic.List`1[[Skyline.DataMiner.Net.Sections.IFieldValidator, SLNetTypes]], mscorlib",
          "$values": []
        }
      }
    ]
  },
  "ID": {
    "$type": "Skyline.DataMiner.Net.Sections.SectionDefinitionID, SLNetTypes",
    "Id": "ffb3508a-aaac-4312-bf6d-c64c5f9cd0a0",
    "ModuleId": "(slc)servicemanagement"
  },
  "IsHidden": false,
  "Name": "Service Profile",
  "ReservationLinkInfo": null,
  "SectionValidators": {
    "$type": "System.Collections.Generic.List`1[[Skyline.DataMiner.Net.Sections.ISectionValidator, SLNetTypes]], mscorlib",
    "$values": []
  }
}