{
  "$type": "Skyline.DataMiner.Net.Sections.CustomSectionDefinition, SLNetTypes",
  "FieldDescriptors": {
    "$type": "System.Collections.Generic.List`1[[Skyline.DataMiner.Net.Sections.FieldDescriptor, SLNetTypes]], mscorlib",
    "$values": [
      {
        "$type": "Skyline.DataMiner.Net.Sections.DomInstanceFieldDescriptor, SLNetTypes",
        "DefaultValue": null,
        "DomDefinitionIds": {
          "$type": "System.Collections.Generic.List`1[[Skyline.DataMiner.Net.Apps.DataMinerObjectModel.DomDefinitionId, SLNetTypes]], mscorlib",
          "$values": [
            {
              "$type": "Skyline.DataMiner.Net.Apps.DataMinerObjectModel.DomDefinitionId, SLNetTypes",
              "Id": "b678f80b-4e71-42b1-ae03-f41d42ea07ef",
              "ModuleId": "(slc)configurations"
            }
          ]
        },
        "FieldType": "System.Guid, mscorlib, Version=4.0.0.0, Culture=neutral, PublicKeyToken=b77a5c561934e089",
        "ID": {
          "$type": "Skyline.DataMiner.Net.Sections.FieldDescriptorID, SLNetTypes",
          "Id": "856cea72-8c62-47e3-9ede-fb1272e65f12"
        },
        "IsHidden": false,
        "IsOptional": true,
        "IsReadonly": false,
        "IsSoftDeleted": false,
        "ModuleId": "(slc)configurations",
        "Name": "Script",
        "Tooltip": "",
        "Validators": {
          "$type": "System.Collections.Generic.List`1[[Skyline.DataMiner.Net.Sections.IFieldValidator, SLNetTypes]], mscorlib",
          "$values": []
        }
      },
      {
        "$type": "Skyline.DataMiner.Net.Sections.FieldDescriptor, SLNetTypes",
        "DefaultValue": null,
        "FieldType": "System.String, mscorlib, Version=4.0.0.0, Culture=neutral, PublicKeyToken=b77a5c561934e089",
        "ID": {
          "$type": "Skyline.DataMiner.Net.Sections.FieldDescriptorID, SLNetTypes",
          "Id": "ad739d3e-9f16-4d76-9868-7deeebe9c2bf"
        },
        "IsHidden": false,
        "IsOptional": false,
        "IsReadonly": false,
        "IsSoftDeleted": false,
        "Name": "Protocol Name",
        "Tooltip": "",
        "Validators": {
          "$type": "System.Collections.Generic.List`1[[Skyline.DataMiner.Net.Sections.IFieldValidator, SLNetTypes]], mscorlib",
          "$values": []
        }
      },
      {
        "$type": "Skyline.DataMiner.Net.Sections.FieldDescriptor, SLNetTypes",
        "DefaultValue": null,
        "FieldType": "System.String, mscorlib, Version=4.0.0.0, Culture=neutral, PublicKeyToken=b77a5c561934e089",
        "ID": {
          "$type": "Skyline.DataMiner.Net.Sections.FieldDescriptorID, SLNetTypes",
          "Id": "40fd89e2-5398-4bcc-b397-0c5e8ecad48f"
        },
        "IsHidden": false,
        "IsOptional": false,
        "IsReadonly": false,
        "IsSoftDeleted": false,
        "Name": "Protocol Version",
        "Tooltip": "",
        "Validators": {
          "$type": "System.Collections.Generic.List`1[[Skyline.DataMiner.Net.Sections.IFieldValidator, SLNetTypes]], mscorlib",
          "$values": []
        }
      },
      {
        "$type": "Skyline.DataMiner.Net.Sections.GenericEnumFieldDescriptor, SLNetTypes",
        "DefaultValue": {
          "$type": "Skyline.DataMiner.Net.Sections.ValueWrapper`1[[System.Int32, mscorlib]], SLNetTypes",
          "Value": 0
        },
        "FieldType": "Skyline.DataMiner.Net.GenericEnums.GenericEnum`1[[System.Int32, mscorlib, Version=4.0.0.0, Culture=neutral, PublicKeyToken=b77a5c561934e089]], SLNetTypes, Version=1.0.0.0, Culture=neutral, PublicKeyToken=9789b1eac4cb1b12",
        "GenericEnumInstance": {
          "$type": "Skyline.DataMiner.Net.GenericEnums.GenericEnum`1[[System.Int32, mscorlib]], SLNetTypes",
          "Entries": {
            "$type": "System.Collections.Generic.List`1[[Skyline.DataMiner.Net.GenericEnums.GenericEnumEntry`1[[System.Int32, mscorlib]], SLNetTypes]], mscorlib",
            "$values": [
              {
                "$type": "Skyline.DataMiner.Net.GenericEnums.GenericEnumEntry`1[[System.Int32, mscorlib]], SLNetTypes",
                "DisplayName": "Untested",
                "IsHidden": false,
                "IsSoftDeleted": false,
                "Value": 0
              },
              {
                "$type": "Skyline.DataMiner.Net.GenericEnums.GenericEnumEntry`1[[System.Int32, mscorlib]], SLNetTypes",
                "DisplayName": "Failed",
                "IsHidden": false,
                "IsSoftDeleted": false,
                "Value": 1
              },
              {
                "$type": "Skyline.DataMiner.Net.GenericEnums.GenericEnumEntry`1[[System.Int32, mscorlib]], SLNetTypes",
                "DisplayName": "Suceeded",
                "IsHidden": false,
                "IsSoftDeleted": false,
                "Value": 2
              }
            ]
          },
          "EnumName": "ProtocolTestState"
        },
        "ID": {
          "$type": "Skyline.DataMiner.Net.Sections.FieldDescriptorID, SLNetTypes",
          "Id": "70b7a32e-0663-4241-890a-7b54dbe2b459"
        },
        "IsHidden": false,
        "IsOptional": false,
        "IsReadonly": false,
        "IsSoftDeleted": false,
        "Name": "State",
        "Tooltip": "",
        "Validators": {
          "$type": "System.Collections.Generic.List`1[[Skyline.DataMiner.Net.Sections.IFieldValidator, SLNetTypes]], mscorlib",
          "$values": []
        }
      },
      {
        "$type": "Skyline.DataMiner.Net.Sections.FieldDescriptor, SLNetTypes",
        "DefaultValue": null,
        "FieldType": "System.String, mscorlib, Version=4.0.0.0, Culture=neutral, PublicKeyToken=b77a5c561934e089",
        "ID": {
          "$type": "Skyline.DataMiner.Net.Sections.FieldDescriptorID, SLNetTypes",
          "Id": "19eec458-e5f5-4cb1-9098-6f8061642511"
        },
        "IsHidden": false,
        "IsOptional": true,
        "IsReadonly": false,
        "IsSoftDeleted": false,
        "Name": "Script Version",
        "Tooltip": "",
        "Validators": {
          "$type": "System.Collections.Generic.List`1[[Skyline.DataMiner.Net.Sections.IFieldValidator, SLNetTypes]], mscorlib",
          "$values": []
        }
      },
      {
        "$type": "Skyline.DataMiner.Net.Sections.FieldDescriptor, SLNetTypes",
        "DefaultValue": null,
        "FieldType": "System.DateTime, mscorlib, Version=4.0.0.0, Culture=neutral, PublicKeyToken=b77a5c561934e089",
        "ID": {
          "$type": "Skyline.DataMiner.Net.Sections.FieldDescriptorID, SLNetTypes",
          "Id": "d81c91ce-6311-40fa-b9b9-57dbbd00cfe3"
        },
        "IsHidden": false,
        "IsOptional": true,
        "IsReadonly": false,
        "IsSoftDeleted": false,
        "Name": "Date",
        "Tooltip": "",
        "Validators": {
          "$type": "System.Collections.Generic.List`1[[Skyline.DataMiner.Net.Sections.IFieldValidator, SLNetTypes]], mscorlib",
          "$values": []
        }
      }
    ]
  },
  "ID": {
    "$type": "Skyline.DataMiner.Net.Sections.SectionDefinitionID, SLNetTypes",
    "Id": "03ce0808-7550-4102-be91-5ce101c5e9c8",
    "ModuleId": "(slc)configurations"
  },
  "IsHidden": false,
  "Name": "Protocol Test Info",
  "ReservationLinkInfo": null,
  "SectionValidators": {
    "$type": "System.Collections.Generic.List`1[[Skyline.DataMiner.Net.Sections.ISectionValidator, SLNetTypes]], mscorlib",
    "$values": []
  }
}