{"Id":{"Id":"9548dac2-dbef-4d14-b319-c608ed7c6ad8","ModuleId":"(slc)servicemanagement"},"Name":"ServiceOrder_Behavior","ParentId":null,"InitialStatusId":"06df5562-cd9b-4b0b-bd45-c58560a8b22a","Statuses":[{"Id":"06df5562-cd9b-4b0b-bd45-c58560a8b22a","DisplayName":"New"},{"Id":"d917fc53-2638-4ab9-9ac6-651ec5312bac","DisplayName":"Acknowledged"},{"Id":"331dc1c2-1950-4c00-a4ae-0aba674a30e6","DisplayName":"In Progress"},{"Id":"260a7073-e54e-4482-a8a7-2b4f2e49c42e","DisplayName":"Completed"},{"Id":"6a01a480-4c38-4db7-b545-72ba05742a7e","DisplayName":"Rejected"},{"Id":"7f13d019-29de-43cb-a510-ab2b2a77e785","DisplayName":"Failed"},{"Id":"f8a8d853-faaf-401c-9865-71e314614023","DisplayName":"Partially Failed"},{"Id":"310ea9e9-f65c-4e11-8b1b-e2c34688ef44","DisplayName":"Held"},{"Id":"23f9fa75-32b8-4e4a-bd65-06a7344d1902","DisplayName":"Pending"},{"Id":"f7e93ddd-cddf-4755-a3e5-0f6ff885dcf5","DisplayName":"Assess Cancellation"},{"Id":"15d08c01-fe63-4d5f-8544-e5b4d66439f5","DisplayName":"Pending Cancellation"},{"Id":"61b80d48-d555-462e-baae-a52b17c85ddb","DisplayName":"Cancelled"}],"StatusSectionDefinitionLinks":[{"FieldDescriptorLinks":[{"FieldDescriptorId":{"Id":"ba13799a-c9b9-4f08-b825-cac8a487af6f"},"Visible":true,"RequiredForStatus":false,"ReadOnly":false,"ClientReadOnly":false},{"FieldDescriptorId":{"Id":"992825d2-778e-4f5f-8fb3-6429f032bdf9"},"Visible":true,"RequiredForStatus":false,"ReadOnly":false,"ClientReadOnly":false},{"FieldDescriptorId":{"Id":"7abc051c-c694-4c06-8860-2e650af11eea"},"Visible":true,"RequiredForStatus":false,"ReadOnly":false,"ClientReadOnly":false},{"FieldDescriptorId":{"Id":"3b0a1b22-9379-4d52-9eae-5308b5c7577f"},"Visible":true,"RequiredForStatus":false,"ReadOnly":false,"ClientReadOnly":false},{"FieldDescriptorId":{"Id":"40fb0b38-0686-4e77-8e77-1a4c36c0e96c"},"Visible":true,"RequiredForStatus":false,"ReadOnly":false,"ClientReadOnly":false},{"FieldDescriptorId":{"Id":"b071ee6f-9a3f-44c9-a187-3a1a78a37a99"},"Visible":true,"RequiredForStatus":false,"ReadOnly":false,"ClientReadOnly":false},{"FieldDescriptorId":{"Id":"eeeca81e-fc47-44dd-b089-05e61b324b37"},"Visible":true,"RequiredForStatus":false,"ReadOnly":false,"ClientReadOnly":false}],"Id":{"StatusId":"06df5562-cd9b-4b0b-bd45-c58560a8b22a","SectionDefinitionId":{"Id":"c8811d15-3006-4478-a29f-f286fb935b46","ModuleId":"(slc)servicemanagement"}},"AllowMultipleSections":false,"IsSoftDeleted":false},{"FieldDescriptorLinks":[{"FieldDescriptorId":{"Id":"853d9a8c-09e3-4e75-b270-5ebf827e9bdf"},"Visible":false,"RequiredForStatus":false,"ReadOnly":false,"ClientReadOnly":false},{"FieldDescriptorId":{"Id":"cad2201c-8663-4656-b53e-91babb984567"},"Visible":false,"RequiredForStatus":false,"ReadOnly":false,"ClientReadOnly":false}],"Id":{"StatusId":"06df5562-cd9b-4b0b-bd45-c58560a8b22a","SectionDefinitionId":{"Id":"b9041ff9-4f7f-4412-822f-18c218a5444d","ModuleId":"(slc)servicemanagement"}},"AllowMultipleSections":true,"IsSoftDeleted":false},{"FieldDescriptorLinks":[{"FieldDescriptorId":{"Id":"ba13799a-c9b9-4f08-b825-cac8a487af6f"},"Visible":true,"RequiredForStatus":false,"ReadOnly":false,"ClientReadOnly":false},{"FieldDescriptorId":{"Id":"992825d2-778e-4f5f-8fb3-6429f032bdf9"},"Visible":true,"RequiredForStatus":false,"ReadOnly":false,"ClientReadOnly":false},{"FieldDescriptorId":{"Id":"7abc051c-c694-4c06-8860-2e650af11eea"},"Visible":true,"RequiredForStatus":false,"ReadOnly":false,"ClientReadOnly":false},{"FieldDescriptorId":{"Id":"3b0a1b22-9379-4d52-9eae-5308b5c7577f"},"Visible":true,"RequiredForStatus":false,"ReadOnly":false,"ClientReadOnly":false},{"FieldDescriptorId":{"Id":"40fb0b38-0686-4e77-8e77-1a4c36c0e96c"},"Visible":true,"RequiredForStatus":false,"ReadOnly":false,"ClientReadOnly":false},{"FieldDescriptorId":{"Id":"b071ee6f-9a3f-44c9-a187-3a1a78a37a99"},"Visible":true,"RequiredForStatus":false,"ReadOnly":false,"ClientReadOnly":false},{"FieldDescriptorId":{"Id":"eeeca81e-fc47-44dd-b089-05e61b324b37"},"Visible":true,"RequiredForStatus":false,"ReadOnly":false,"ClientReadOnly":false}],"Id":{"StatusId":"d917fc53-2638-4ab9-9ac6-651ec5312bac","SectionDefinitionId":{"Id":"c8811d15-3006-4478-a29f-f286fb935b46","ModuleId":"(slc)servicemanagement"}},"AllowMultipleSections":false,"IsSoftDeleted":false},{"FieldDescriptorLinks":[{"FieldDescriptorId":{"Id":"853d9a8c-09e3-4e75-b270-5ebf827e9bdf"},"Visible":false,"RequiredForStatus":false,"ReadOnly":false,"ClientReadOnly":false},{"FieldDescriptorId":{"Id":"cad2201c-8663-4656-b53e-91babb984567"},"Visible":false,"RequiredForStatus":false,"ReadOnly":false,"ClientReadOnly":false}],"Id":{"StatusId":"d917fc53-2638-4ab9-9ac6-651ec5312bac","SectionDefinitionId":{"Id":"b9041ff9-4f7f-4412-822f-18c218a5444d","ModuleId":"(slc)servicemanagement"}},"AllowMultipleSections":true,"IsSoftDeleted":false},{"FieldDescriptorLinks":[{"FieldDescriptorId":{"Id":"ba13799a-c9b9-4f08-b825-cac8a487af6f"},"Visible":true,"RequiredForStatus":false,"ReadOnly":false,"ClientReadOnly":false},{"FieldDescriptorId":{"Id":"992825d2-778e-4f5f-8fb3-6429f032bdf9"},"Visible":true,"RequiredForStatus":false,"ReadOnly":false,"ClientReadOnly":false},{"FieldDescriptorId":{"Id":"7abc051c-c694-4c06-8860-2e650af11eea"},"Visible":true,"RequiredForStatus":false,"ReadOnly":false,"ClientReadOnly":false},{"FieldDescriptorId":{"Id":"3b0a1b22-9379-4d52-9eae-5308b5c7577f"},"Visible":true,"RequiredForStatus":false,"ReadOnly":false,"ClientReadOnly":false},{"FieldDescriptorId":{"Id":"40fb0b38-0686-4e77-8e77-1a4c36c0e96c"},"Visible":true,"RequiredForStatus":false,"ReadOnly":false,"ClientReadOnly":false},{"FieldDescriptorId":{"Id":"b071ee6f-9a3f-44c9-a187-3a1a78a37a99"},"Visible":true,"RequiredForStatus":false,"ReadOnly":false,"ClientReadOnly":false},{"FieldDescriptorId":{"Id":"eeeca81e-fc47-44dd-b089-05e61b324b37"},"Visible":true,"RequiredForStatus":false,"ReadOnly":false,"ClientReadOnly":false}],"Id":{"StatusId":"331dc1c2-1950-4c00-a4ae-0aba674a30e6","SectionDefinitionId":{"Id":"c8811d15-3006-4478-a29f-f286fb935b46","ModuleId":"(slc)servicemanagement"}},"AllowMultipleSections":false,"IsSoftDeleted":false},{"FieldDescriptorLinks":[{"FieldDescriptorId":{"Id":"853d9a8c-09e3-4e75-b270-5ebf827e9bdf"},"Visible":false,"RequiredForStatus":false,"ReadOnly":false,"ClientReadOnly":false},{"FieldDescriptorId":{"Id":"cad2201c-8663-4656-b53e-91babb984567"},"Visible":false,"RequiredForStatus":false,"ReadOnly":false,"ClientReadOnly":false}],"Id":{"StatusId":"331dc1c2-1950-4c00-a4ae-0aba674a30e6","SectionDefinitionId":{"Id":"b9041ff9-4f7f-4412-822f-18c218a5444d","ModuleId":"(slc)servicemanagement"}},"AllowMultipleSections":true,"IsSoftDeleted":false},{"FieldDescriptorLinks":[{"FieldDescriptorId":{"Id":"ba13799a-c9b9-4f08-b825-cac8a487af6f"},"Visible":true,"RequiredForStatus":false,"ReadOnly":false,"ClientReadOnly":false},{"FieldDescriptorId":{"Id":"992825d2-778e-4f5f-8fb3-6429f032bdf9"},"Visible":true,"RequiredForStatus":false,"ReadOnly":false,"ClientReadOnly":false},{"FieldDescriptorId":{"Id":"7abc051c-c694-4c06-8860-2e650af11eea"},"Visible":true,"RequiredForStatus":false,"ReadOnly":false,"ClientReadOnly":false},{"FieldDescriptorId":{"Id":"3b0a1b22-9379-4d52-9eae-5308b5c7577f"},"Visible":true,"RequiredForStatus":false,"ReadOnly":false,"ClientReadOnly":false},{"FieldDescriptorId":{"Id":"40fb0b38-0686-4e77-8e77-1a4c36c0e96c"},"Visible":true,"RequiredForStatus":false,"ReadOnly":false,"ClientReadOnly":false},{"FieldDescriptorId":{"Id":"b071ee6f-9a3f-44c9-a187-3a1a78a37a99"},"Visible":true,"RequiredForStatus":false,"ReadOnly":false,"ClientReadOnly":false},{"FieldDescriptorId":{"Id":"eeeca81e-fc47-44dd-b089-05e61b324b37"},"Visible":true,"RequiredForStatus":false,"ReadOnly":false,"ClientReadOnly":false}],"Id":{"StatusId":"260a7073-e54e-4482-a8a7-2b4f2e49c42e","SectionDefinitionId":{"Id":"c8811d15-3006-4478-a29f-f286fb935b46","ModuleId":"(slc)servicemanagement"}},"AllowMultipleSections":false,"IsSoftDeleted":false},{"FieldDescriptorLinks":[{"FieldDescriptorId":{"Id":"853d9a8c-09e3-4e75-b270-5ebf827e9bdf"},"Visible":false,"RequiredForStatus":false,"ReadOnly":false,"ClientReadOnly":false},{"FieldDescriptorId":{"Id":"cad2201c-8663-4656-b53e-91babb984567"},"Visible":false,"RequiredForStatus":false,"ReadOnly":false,"ClientReadOnly":false}],"Id":{"StatusId":"260a7073-e54e-4482-a8a7-2b4f2e49c42e","SectionDefinitionId":{"Id":"b9041ff9-4f7f-4412-822f-18c218a5444d","ModuleId":"(slc)servicemanagement"}},"AllowMultipleSections":true,"IsSoftDeleted":false},{"FieldDescriptorLinks":[{"FieldDescriptorId":{"Id":"ba13799a-c9b9-4f08-b825-cac8a487af6f"},"Visible":true,"RequiredForStatus":false,"ReadOnly":false,"ClientReadOnly":false},{"FieldDescriptorId":{"Id":"992825d2-778e-4f5f-8fb3-6429f032bdf9"},"Visible":true,"RequiredForStatus":false,"ReadOnly":false,"ClientReadOnly":false},{"FieldDescriptorId":{"Id":"7abc051c-c694-4c06-8860-2e650af11eea"},"Visible":true,"RequiredForStatus":false,"ReadOnly":false,"ClientReadOnly":false},{"FieldDescriptorId":{"Id":"3b0a1b22-9379-4d52-9eae-5308b5c7577f"},"Visible":true,"RequiredForStatus":false,"ReadOnly":false,"ClientReadOnly":false},{"FieldDescriptorId":{"Id":"40fb0b38-0686-4e77-8e77-1a4c36c0e96c"},"Visible":true,"RequiredForStatus":false,"ReadOnly":false,"ClientReadOnly":false},{"FieldDescriptorId":{"Id":"b071ee6f-9a3f-44c9-a187-3a1a78a37a99"},"Visible":true,"RequiredForStatus":false,"ReadOnly":false,"ClientReadOnly":false},{"FieldDescriptorId":{"Id":"eeeca81e-fc47-44dd-b089-05e61b324b37"},"Visible":true,"RequiredForStatus":false,"ReadOnly":false,"ClientReadOnly":false}],"Id":{"StatusId":"6a01a480-4c38-4db7-b545-72ba05742a7e","SectionDefinitionId":{"Id":"c8811d15-3006-4478-a29f-f286fb935b46","ModuleId":"(slc)servicemanagement"}},"AllowMultipleSections":false,"IsSoftDeleted":false},{"FieldDescriptorLinks":[{"FieldDescriptorId":{"Id":"853d9a8c-09e3-4e75-b270-5ebf827e9bdf"},"Visible":false,"RequiredForStatus":false,"ReadOnly":false,"ClientReadOnly":false},{"FieldDescriptorId":{"Id":"cad2201c-8663-4656-b53e-91babb984567"},"Visible":false,"RequiredForStatus":false,"ReadOnly":false,"ClientReadOnly":false}],"Id":{"StatusId":"6a01a480-4c38-4db7-b545-72ba05742a7e","SectionDefinitionId":{"Id":"b9041ff9-4f7f-4412-822f-18c218a5444d","ModuleId":"(slc)servicemanagement"}},"AllowMultipleSections":true,"IsSoftDeleted":false},{"FieldDescriptorLinks":[{"FieldDescriptorId":{"Id":"ba13799a-c9b9-4f08-b825-cac8a487af6f"},"Visible":true,"RequiredForStatus":false,"ReadOnly":false,"ClientReadOnly":false},{"FieldDescriptorId":{"Id":"992825d2-778e-4f5f-8fb3-6429f032bdf9"},"Visible":true,"RequiredForStatus":false,"ReadOnly":false,"ClientReadOnly":false},{"FieldDescriptorId":{"Id":"7abc051c-c694-4c06-8860-2e650af11eea"},"Visible":true,"RequiredForStatus":false,"ReadOnly":false,"ClientReadOnly":false},{"FieldDescriptorId":{"Id":"3b0a1b22-9379-4d52-9eae-5308b5c7577f"},"Visible":true,"RequiredForStatus":false,"ReadOnly":false,"ClientReadOnly":false},{"FieldDescriptorId":{"Id":"40fb0b38-0686-4e77-8e77-1a4c36c0e96c"},"Visible":true,"RequiredForStatus":false,"ReadOnly":false,"ClientReadOnly":false},{"FieldDescriptorId":{"Id":"b071ee6f-9a3f-44c9-a187-3a1a78a37a99"},"Visible":true,"RequiredForStatus":false,"ReadOnly":false,"ClientReadOnly":false},{"FieldDescriptorId":{"Id":"eeeca81e-fc47-44dd-b089-05e61b324b37"},"Visible":true,"RequiredForStatus":false,"ReadOnly":false,"ClientReadOnly":false}],"Id":{"StatusId":"7f13d019-29de-43cb-a510-ab2b2a77e785","SectionDefinitionId":{"Id":"c8811d15-3006-4478-a29f-f286fb935b46","ModuleId":"(slc)servicemanagement"}},"AllowMultipleSections":false,"IsSoftDeleted":false},{"FieldDescriptorLinks":[{"FieldDescriptorId":{"Id":"853d9a8c-09e3-4e75-b270-5ebf827e9bdf"},"Visible":false,"RequiredForStatus":false,"ReadOnly":false,"ClientReadOnly":false},{"FieldDescriptorId":{"Id":"cad2201c-8663-4656-b53e-91babb984567"},"Visible":false,"RequiredForStatus":false,"ReadOnly":false,"ClientReadOnly":false}],"Id":{"StatusId":"7f13d019-29de-43cb-a510-ab2b2a77e785","SectionDefinitionId":{"Id":"b9041ff9-4f7f-4412-822f-18c218a5444d","ModuleId":"(slc)servicemanagement"}},"AllowMultipleSections":true,"IsSoftDeleted":false},{"FieldDescriptorLinks":[{"FieldDescriptorId":{"Id":"ba13799a-c9b9-4f08-b825-cac8a487af6f"},"Visible":true,"RequiredForStatus":false,"ReadOnly":false,"ClientReadOnly":false},{"FieldDescriptorId":{"Id":"992825d2-778e-4f5f-8fb3-6429f032bdf9"},"Visible":true,"RequiredForStatus":false,"ReadOnly":false,"ClientReadOnly":false},{"FieldDescriptorId":{"Id":"7abc051c-c694-4c06-8860-2e650af11eea"},"Visible":true,"RequiredForStatus":false,"ReadOnly":false,"ClientReadOnly":false},{"FieldDescriptorId":{"Id":"3b0a1b22-9379-4d52-9eae-5308b5c7577f"},"Visible":true,"RequiredForStatus":false,"ReadOnly":false,"ClientReadOnly":false},{"FieldDescriptorId":{"Id":"40fb0b38-0686-4e77-8e77-1a4c36c0e96c"},"Visible":true,"RequiredForStatus":false,"ReadOnly":false,"ClientReadOnly":false},{"FieldDescriptorId":{"Id":"b071ee6f-9a3f-44c9-a187-3a1a78a37a99"},"Visible":true,"RequiredForStatus":false,"ReadOnly":false,"ClientReadOnly":false},{"FieldDescriptorId":{"Id":"eeeca81e-fc47-44dd-b089-05e61b324b37"},"Visible":true,"RequiredForStatus":false,"ReadOnly":false,"ClientReadOnly":false}],"Id":{"StatusId":"f8a8d853-faaf-401c-9865-71e314614023","SectionDefinitionId":{"Id":"c8811d15-3006-4478-a29f-f286fb935b46","ModuleId":"(slc)servicemanagement"}},"AllowMultipleSections":false,"IsSoftDeleted":false},{"FieldDescriptorLinks":[{"FieldDescriptorId":{"Id":"853d9a8c-09e3-4e75-b270-5ebf827e9bdf"},"Visible":false,"RequiredForStatus":false,"ReadOnly":false,"ClientReadOnly":false},{"FieldDescriptorId":{"Id":"cad2201c-8663-4656-b53e-91babb984567"},"Visible":false,"RequiredForStatus":false,"ReadOnly":false,"ClientReadOnly":false}],"Id":{"StatusId":"f8a8d853-faaf-401c-9865-71e314614023","SectionDefinitionId":{"Id":"b9041ff9-4f7f-4412-822f-18c218a5444d","ModuleId":"(slc)servicemanagement"}},"AllowMultipleSections":true,"IsSoftDeleted":false},{"FieldDescriptorLinks":[{"FieldDescriptorId":{"Id":"ba13799a-c9b9-4f08-b825-cac8a487af6f"},"Visible":true,"RequiredForStatus":false,"ReadOnly":false,"ClientReadOnly":false},{"FieldDescriptorId":{"Id":"992825d2-778e-4f5f-8fb3-6429f032bdf9"},"Visible":true,"RequiredForStatus":false,"ReadOnly":false,"ClientReadOnly":false},{"FieldDescriptorId":{"Id":"7abc051c-c694-4c06-8860-2e650af11eea"},"Visible":true,"RequiredForStatus":false,"ReadOnly":false,"ClientReadOnly":false},{"FieldDescriptorId":{"Id":"3b0a1b22-9379-4d52-9eae-5308b5c7577f"},"Visible":true,"RequiredForStatus":false,"ReadOnly":false,"ClientReadOnly":false},{"FieldDescriptorId":{"Id":"40fb0b38-0686-4e77-8e77-1a4c36c0e96c"},"Visible":true,"RequiredForStatus":false,"ReadOnly":false,"ClientReadOnly":false},{"FieldDescriptorId":{"Id":"b071ee6f-9a3f-44c9-a187-3a1a78a37a99"},"Visible":true,"RequiredForStatus":false,"ReadOnly":false,"ClientReadOnly":false},{"FieldDescriptorId":{"Id":"eeeca81e-fc47-44dd-b089-05e61b324b37"},"Visible":true,"RequiredForStatus":false,"ReadOnly":false,"ClientReadOnly":false}],"Id":{"StatusId":"310ea9e9-f65c-4e11-8b1b-e2c34688ef44","SectionDefinitionId":{"Id":"c8811d15-3006-4478-a29f-f286fb935b46","ModuleId":"(slc)servicemanagement"}},"AllowMultipleSections":false,"IsSoftDeleted":false},{"FieldDescriptorLinks":[{"FieldDescriptorId":{"Id":"853d9a8c-09e3-4e75-b270-5ebf827e9bdf"},"Visible":false,"RequiredForStatus":false,"ReadOnly":false,"ClientReadOnly":false},{"FieldDescriptorId":{"Id":"cad2201c-8663-4656-b53e-91babb984567"},"Visible":false,"RequiredForStatus":false,"ReadOnly":false,"ClientReadOnly":false}],"Id":{"StatusId":"310ea9e9-f65c-4e11-8b1b-e2c34688ef44","SectionDefinitionId":{"Id":"b9041ff9-4f7f-4412-822f-18c218a5444d","ModuleId":"(slc)servicemanagement"}},"AllowMultipleSections":true,"IsSoftDeleted":false},{"FieldDescriptorLinks":[{"FieldDescriptorId":{"Id":"ba13799a-c9b9-4f08-b825-cac8a487af6f"},"Visible":true,"RequiredForStatus":false,"ReadOnly":false,"ClientReadOnly":false},{"FieldDescriptorId":{"Id":"992825d2-778e-4f5f-8fb3-6429f032bdf9"},"Visible":true,"RequiredForStatus":false,"ReadOnly":false,"ClientReadOnly":false},{"FieldDescriptorId":{"Id":"7abc051c-c694-4c06-8860-2e650af11eea"},"Visible":true,"RequiredForStatus":false,"ReadOnly":false,"ClientReadOnly":false},{"FieldDescriptorId":{"Id":"3b0a1b22-9379-4d52-9eae-5308b5c7577f"},"Visible":true,"RequiredForStatus":false,"ReadOnly":false,"ClientReadOnly":false},{"FieldDescriptorId":{"Id":"40fb0b38-0686-4e77-8e77-1a4c36c0e96c"},"Visible":true,"RequiredForStatus":false,"ReadOnly":false,"ClientReadOnly":false},{"FieldDescriptorId":{"Id":"b071ee6f-9a3f-44c9-a187-3a1a78a37a99"},"Visible":true,"RequiredForStatus":false,"ReadOnly":false,"ClientReadOnly":false},{"FieldDescriptorId":{"Id":"eeeca81e-fc47-44dd-b089-05e61b324b37"},"Visible":true,"RequiredForStatus":false,"ReadOnly":false,"ClientReadOnly":false}],"Id":{"StatusId":"23f9fa75-32b8-4e4a-bd65-06a7344d1902","SectionDefinitionId":{"Id":"c8811d15-3006-4478-a29f-f286fb935b46","ModuleId":"(slc)servicemanagement"}},"AllowMultipleSections":false,"IsSoftDeleted":false},{"FieldDescriptorLinks":[{"FieldDescriptorId":{"Id":"853d9a8c-09e3-4e75-b270-5ebf827e9bdf"},"Visible":false,"RequiredForStatus":false,"ReadOnly":false,"ClientReadOnly":false},{"FieldDescriptorId":{"Id":"cad2201c-8663-4656-b53e-91babb984567"},"Visible":false,"RequiredForStatus":false,"ReadOnly":false,"ClientReadOnly":false}],"Id":{"StatusId":"23f9fa75-32b8-4e4a-bd65-06a7344d1902","SectionDefinitionId":{"Id":"b9041ff9-4f7f-4412-822f-18c218a5444d","ModuleId":"(slc)servicemanagement"}},"AllowMultipleSections":true,"IsSoftDeleted":false},{"FieldDescriptorLinks":[{"FieldDescriptorId":{"Id":"ba13799a-c9b9-4f08-b825-cac8a487af6f"},"Visible":true,"RequiredForStatus":false,"ReadOnly":false,"ClientReadOnly":false},{"FieldDescriptorId":{"Id":"992825d2-778e-4f5f-8fb3-6429f032bdf9"},"Visible":true,"RequiredForStatus":false,"ReadOnly":false,"ClientReadOnly":false},{"FieldDescriptorId":{"Id":"7abc051c-c694-4c06-8860-2e650af11eea"},"Visible":true,"RequiredForStatus":false,"ReadOnly":false,"ClientReadOnly":false},{"FieldDescriptorId":{"Id":"3b0a1b22-9379-4d52-9eae-5308b5c7577f"},"Visible":true,"RequiredForStatus":false,"ReadOnly":false,"ClientReadOnly":false},{"FieldDescriptorId":{"Id":"40fb0b38-0686-4e77-8e77-1a4c36c0e96c"},"Visible":true,"RequiredForStatus":false,"ReadOnly":false,"ClientReadOnly":false},{"FieldDescriptorId":{"Id":"b071ee6f-9a3f-44c9-a187-3a1a78a37a99"},"Visible":true,"RequiredForStatus":false,"ReadOnly":false,"ClientReadOnly":false},{"FieldDescriptorId":{"Id":"eeeca81e-fc47-44dd-b089-05e61b324b37"},"Visible":true,"RequiredForStatus":false,"ReadOnly":false,"ClientReadOnly":false}],"Id":{"StatusId":"f7e93ddd-cddf-4755-a3e5-0f6ff885dcf5","SectionDefinitionId":{"Id":"c8811d15-3006-4478-a29f-f286fb935b46","ModuleId":"(slc)servicemanagement"}},"AllowMultipleSections":false,"IsSoftDeleted":false},{"FieldDescriptorLinks":[{"FieldDescriptorId":{"Id":"853d9a8c-09e3-4e75-b270-5ebf827e9bdf"},"Visible":false,"RequiredForStatus":false,"ReadOnly":false,"ClientReadOnly":false},{"FieldDescriptorId":{"Id":"cad2201c-8663-4656-b53e-91babb984567"},"Visible":false,"RequiredForStatus":false,"ReadOnly":false,"ClientReadOnly":false}],"Id":{"StatusId":"f7e93ddd-cddf-4755-a3e5-0f6ff885dcf5","SectionDefinitionId":{"Id":"b9041ff9-4f7f-4412-822f-18c218a5444d","ModuleId":"(slc)servicemanagement"}},"AllowMultipleSections":true,"IsSoftDeleted":false},{"FieldDescriptorLinks":[{"FieldDescriptorId":{"Id":"ba13799a-c9b9-4f08-b825-cac8a487af6f"},"Visible":true,"RequiredForStatus":false,"ReadOnly":false,"ClientReadOnly":false},{"FieldDescriptorId":{"Id":"992825d2-778e-4f5f-8fb3-6429f032bdf9"},"Visible":true,"RequiredForStatus":false,"ReadOnly":false,"ClientReadOnly":false},{"FieldDescriptorId":{"Id":"7abc051c-c694-4c06-8860-2e650af11eea"},"Visible":true,"RequiredForStatus":false,"ReadOnly":false,"ClientReadOnly":false},{"FieldDescriptorId":{"Id":"3b0a1b22-9379-4d52-9eae-5308b5c7577f"},"Visible":true,"RequiredForStatus":false,"ReadOnly":false,"ClientReadOnly":false},{"FieldDescriptorId":{"Id":"40fb0b38-0686-4e77-8e77-1a4c36c0e96c"},"Visible":true,"RequiredForStatus":false,"ReadOnly":false,"ClientReadOnly":false},{"FieldDescriptorId":{"Id":"b071ee6f-9a3f-44c9-a187-3a1a78a37a99"},"Visible":true,"RequiredForStatus":false,"ReadOnly":false,"ClientReadOnly":false},{"FieldDescriptorId":{"Id":"eeeca81e-fc47-44dd-b089-05e61b324b37"},"Visible":true,"RequiredForStatus":false,"ReadOnly":false,"ClientReadOnly":false}],"Id":{"StatusId":"15d08c01-fe63-4d5f-8544-e5b4d66439f5","SectionDefinitionId":{"Id":"c8811d15-3006-4478-a29f-f286fb935b46","ModuleId":"(slc)servicemanagement"}},"AllowMultipleSections":false,"IsSoftDeleted":false},{"FieldDescriptorLinks":[{"FieldDescriptorId":{"Id":"853d9a8c-09e3-4e75-b270-5ebf827e9bdf"},"Visible":false,"RequiredForStatus":false,"ReadOnly":false,"ClientReadOnly":false},{"FieldDescriptorId":{"Id":"cad2201c-8663-4656-b53e-91babb984567"},"Visible":false,"RequiredForStatus":false,"ReadOnly":false,"ClientReadOnly":false}],"Id":{"StatusId":"15d08c01-fe63-4d5f-8544-e5b4d66439f5","SectionDefinitionId":{"Id":"b9041ff9-4f7f-4412-822f-18c218a5444d","ModuleId":"(slc)servicemanagement"}},"AllowMultipleSections":true,"IsSoftDeleted":false},{"FieldDescriptorLinks":[{"FieldDescriptorId":{"Id":"ba13799a-c9b9-4f08-b825-cac8a487af6f"},"Visible":true,"RequiredForStatus":false,"ReadOnly":false,"ClientReadOnly":false},{"FieldDescriptorId":{"Id":"992825d2-778e-4f5f-8fb3-6429f032bdf9"},"Visible":true,"RequiredForStatus":false,"ReadOnly":false,"ClientReadOnly":false},{"FieldDescriptorId":{"Id":"7abc051c-c694-4c06-8860-2e650af11eea"},"Visible":true,"RequiredForStatus":false,"ReadOnly":false,"ClientReadOnly":false},{"FieldDescriptorId":{"Id":"3b0a1b22-9379-4d52-9eae-5308b5c7577f"},"Visible":true,"RequiredForStatus":false,"ReadOnly":false,"ClientReadOnly":false},{"FieldDescriptorId":{"Id":"40fb0b38-0686-4e77-8e77-1a4c36c0e96c"},"Visible":true,"RequiredForStatus":false,"ReadOnly":false,"ClientReadOnly":false},{"FieldDescriptorId":{"Id":"b071ee6f-9a3f-44c9-a187-3a1a78a37a99"},"Visible":true,"RequiredForStatus":false,"ReadOnly":false,"ClientReadOnly":false},{"FieldDescriptorId":{"Id":"eeeca81e-fc47-44dd-b089-05e61b324b37"},"Visible":true,"RequiredForStatus":false,"ReadOnly":false,"ClientReadOnly":false}],"Id":{"StatusId":"61b80d48-d555-462e-baae-a52b17c85ddb","SectionDefinitionId":{"Id":"c8811d15-3006-4478-a29f-f286fb935b46","ModuleId":"(slc)servicemanagement"}},"AllowMultipleSections":false,"IsSoftDeleted":false},{"FieldDescriptorLinks":[{"FieldDescriptorId":{"Id":"853d9a8c-09e3-4e75-b270-5ebf827e9bdf"},"Visible":false,"RequiredForStatus":false,"ReadOnly":false,"ClientReadOnly":false},{"FieldDescriptorId":{"Id":"cad2201c-8663-4656-b53e-91babb984567"},"Visible":false,"RequiredForStatus":false,"ReadOnly":false,"ClientReadOnly":false}],"Id":{"StatusId":"61b80d48-d555-462e-baae-a52b17c85ddb","SectionDefinitionId":{"Id":"b9041ff9-4f7f-4412-822f-18c218a5444d","ModuleId":"(slc)servicemanagement"}},"AllowMultipleSections":true,"IsSoftDeleted":false}],"StatusTransitions":[{"Id":"new_to_acknowledged","FromStatusId":"06df5562-cd9b-4b0b-bd45-c58560a8b22a","ToStatusId":"d917fc53-2638-4ab9-9ac6-651ec5312bac","FlowLevel":0},{"Id":"new_to_rejected","FromStatusId":"06df5562-cd9b-4b0b-bd45-c58560a8b22a","ToStatusId":"6a01a480-4c38-4db7-b545-72ba05742a7e","FlowLevel":1},{"Id":"acknowledged_to_rejected","FromStatusId":"d917fc53-2638-4ab9-9ac6-651ec5312bac","ToStatusId":"6a01a480-4c38-4db7-b545-72ba05742a7e","FlowLevel":2},{"Id":"acknowledged_to_inprogress","FromStatusId":"d917fc53-2638-4ab9-9ac6-651ec5312bac","ToStatusId":"331dc1c2-1950-4c00-a4ae-0aba674a30e6","FlowLevel":0},{"Id":"inprogress_to_completed","FromStatusId":"331dc1c2-1950-4c00-a4ae-0aba674a30e6","ToStatusId":"260a7073-e54e-4482-a8a7-2b4f2e49c42e","FlowLevel":0},{"Id":"inprogress_to_failed","FromStatusId":"331dc1c2-1950-4c00-a4ae-0aba674a30e6","ToStatusId":"7f13d019-29de-43cb-a510-ab2b2a77e785","FlowLevel":3},{"Id":"inprogress_to_partial","FromStatusId":"331dc1c2-1950-4c00-a4ae-0aba674a30e6","ToStatusId":"f8a8d853-faaf-401c-9865-71e314614023","FlowLevel":4},{"Id":"inprogress_to_held","FromStatusId":"331dc1c2-1950-4c00-a4ae-0aba674a30e6","ToStatusId":"310ea9e9-f65c-4e11-8b1b-e2c34688ef44","FlowLevel":5},{"Id":"inprogress_to_pending","FromStatusId":"331dc1c2-1950-4c00-a4ae-0aba674a30e6","ToStatusId":"23f9fa75-32b8-4e4a-bd65-06a7344d1902","FlowLevel":6},{"Id":"pending_to_assesscancellation","FromStatusId":"23f9fa75-32b8-4e4a-bd65-06a7344d1902","ToStatusId":"f7e93ddd-cddf-4755-a3e5-0f6ff885dcf5","FlowLevel":6},{"Id":"assesscancellation_to_pendingcancellation","FromStatusId":"f7e93ddd-cddf-4755-a3e5-0f6ff885dcf5","ToStatusId":"15d08c01-fe63-4d5f-8544-e5b4d66439f5","FlowLevel":6},{"Id":"pendingcancellation_to_cancelled","FromStatusId":"15d08c01-fe63-4d5f-8544-e5b4d66439f5","ToStatusId":"61b80d48-d555-462e-baae-a52b17c85ddb","FlowLevel":6},{"Id":"held_to_inprogress","FromStatusId":"310ea9e9-f65c-4e11-8b1b-e2c34688ef44","ToStatusId":"331dc1c2-1950-4c00-a4ae-0aba674a30e6","FlowLevel":7},{"Id":"assesscancellation_to_held","FromStatusId":"f7e93ddd-cddf-4755-a3e5-0f6ff885dcf5","ToStatusId":"310ea9e9-f65c-4e11-8b1b-e2c34688ef44","FlowLevel":7},{"Id":"assesscancellation_to_pending","FromStatusId":"f7e93ddd-cddf-4755-a3e5-0f6ff885dcf5","ToStatusId":"23f9fa75-32b8-4e4a-bd65-06a7344d1902","FlowLevel":8},{"Id":"held_to_assesscancellation","FromStatusId":"310ea9e9-f65c-4e11-8b1b-e2c34688ef44","ToStatusId":"f7e93ddd-cddf-4755-a3e5-0f6ff885dcf5","FlowLevel":5},{"Id":"pending_to_inprogress","FromStatusId":"23f9fa75-32b8-4e4a-bd65-06a7344d1902","ToStatusId":"331dc1c2-1950-4c00-a4ae-0aba674a30e6","FlowLevel":6}],"ButtonDefinitions":[{"$type":"Skyline.DataMiner.Net.Apps.DataMinerObjectModel.Buttons.DomInstanceButtonDefinition, SLNetTypes","Id":"new_to_reject","Layout":{"Text":"Reject","Icon":"","ToolTip":"","Order":1},"VisibilityCondition":{"$type":"Skyline.DataMiner.Net.Apps.DataMinerObjectModel.Conditions.StatusCondition, SLNetTypes","Statuses":["06df5562-cd9b-4b0b-bd45-c58560a8b22a"]},"ActionDefinitionIds":["new_to_rejected"]},{"$type":"Skyline.DataMiner.Net.Apps.DataMinerObjectModel.Buttons.DomInstanceButtonDefinition, SLNetTypes","Id":"acknowledged_to_reject","Layout":{"Text":"Reject","Icon":"","ToolTip":"","Order":1},"VisibilityCondition":{"$type":"Skyline.DataMiner.Net.Apps.DataMinerObjectModel.Conditions.StatusCondition, SLNetTypes","Statuses":["d917fc53-2638-4ab9-9ac6-651ec5312bac"]},"ActionDefinitionIds":["acknowledged_to_rejected"]},{"$type":"Skyline.DataMiner.Net.Apps.DataMinerObjectModel.Buttons.DomInstanceButtonDefinition, SLNetTypes","Id":"inprogress_to_failed","Layout":{"Text":"Failed","Icon":"","ToolTip":"","Order":2},"VisibilityCondition":{"$type":"Skyline.DataMiner.Net.Apps.DataMinerObjectModel.Conditions.StatusCondition, SLNetTypes","Statuses":["331dc1c2-1950-4c00-a4ae-0aba674a30e6"]},"ActionDefinitionIds":["inprogess_to_failed"]},{"$type":"Skyline.DataMiner.Net.Apps.DataMinerObjectModel.Buttons.DomInstanceButtonDefinition, SLNetTypes","Id":"inprogress_to_partial","Layout":{"Text":"Partially Failed","Icon":"","ToolTip":"","Order":1},"VisibilityCondition":{"$type":"Skyline.DataMiner.Net.Apps.DataMinerObjectModel.Conditions.StatusCondition, SLNetTypes","Statuses":["331dc1c2-1950-4c00-a4ae-0aba674a30e6"]},"ActionDefinitionIds":["inprogress_to_partial"]},{"$type":"Skyline.DataMiner.Net.Apps.DataMinerObjectModel.Buttons.DomInstanceButtonDefinition, SLNetTypes","Id":"new_to_acknowledged","Layout":{"Text":"Acknowledge","Icon":"","ToolTip":"","Order":0},"VisibilityCondition":{"$type":"Skyline.DataMiner.Net.Apps.DataMinerObjectModel.Conditions.StatusCondition, SLNetTypes","Statuses":["06df5562-cd9b-4b0b-bd45-c58560a8b22a"]},"ActionDefinitionIds":["new_to_acknowledged"]},{"$type":"Skyline.DataMiner.Net.Apps.DataMinerObjectModel.Buttons.DomInstanceButtonDefinition, SLNetTypes","Id":"acknowledged_to_inprogress","Layout":{"Text":"Initialize","Icon":"","ToolTip":"","Order":0},"VisibilityCondition":{"$type":"Skyline.DataMiner.Net.Apps.DataMinerObjectModel.Conditions.StatusCondition, SLNetTypes","Statuses":["d917fc53-2638-4ab9-9ac6-651ec5312bac"]},"ActionDefinitionIds":["acknowledged_to_inprogress"]},{"$type":"Skyline.DataMiner.Net.Apps.DataMinerObjectModel.Buttons.DomInstanceButtonDefinition, SLNetTypes","Id":"inprogress_to_complete","Layout":{"Text":"Complete","Icon":"","ToolTip":"","Order":0},"VisibilityCondition":{"$type":"Skyline.DataMiner.Net.Apps.DataMinerObjectModel.Conditions.StatusCondition, SLNetTypes","Statuses":["331dc1c2-1950-4c00-a4ae-0aba674a30e6"]},"ActionDefinitionIds":["inprogress_to_completed"]},{"$type":"Skyline.DataMiner.Net.Apps.DataMinerObjectModel.Buttons.DomInstanceButtonDefinition, SLNetTypes","Id":"inprogress_to_held","Layout":{"Text":"Issue Detected","Icon":"","ToolTip":"","Order":4},"VisibilityCondition":{"$type":"Skyline.DataMiner.Net.Apps.DataMinerObjectModel.Conditions.StatusCondition, SLNetTypes","Statuses":["331dc1c2-1950-4c00-a4ae-0aba674a30e6"]},"ActionDefinitionIds":["inprogress_to_held"]},{"$type":"Skyline.DataMiner.Net.Apps.DataMinerObjectModel.Buttons.DomInstanceButtonDefinition, SLNetTypes","Id":"inprogress_to_pending","Layout":{"Text":"Information Missing","Icon":"","ToolTip":"","Order":3},"VisibilityCondition":{"$type":"Skyline.DataMiner.Net.Apps.DataMinerObjectModel.Conditions.StatusCondition, SLNetTypes","Statuses":["331dc1c2-1950-4c00-a4ae-0aba674a30e6"]},"ActionDefinitionIds":["inprogress_to_pending"]},{"$type":"Skyline.DataMiner.Net.Apps.DataMinerObjectModel.Buttons.DomInstanceButtonDefinition, SLNetTypes","Id":"held_to_assesscancellation","Layout":{"Text":"Request Cancellation","Icon":"","ToolTip":"","Order":1},"VisibilityCondition":{"$type":"Skyline.DataMiner.Net.Apps.DataMinerObjectModel.Conditions.StatusCondition, SLNetTypes","Statuses":["310ea9e9-f65c-4e11-8b1b-e2c34688ef44"]},"ActionDefinitionIds":["held_to_assesscancellation"]},{"$type":"Skyline.DataMiner.Net.Apps.DataMinerObjectModel.Buttons.DomInstanceButtonDefinition, SLNetTypes","Id":"pendingcancellation_to_cancelled","Layout":{"Text":"Cancel","Icon":"","ToolTip":"","Order":0},"VisibilityCondition":{"$type":"Skyline.DataMiner.Net.Apps.DataMinerObjectModel.Conditions.StatusCondition, SLNetTypes","Statuses":["15d08c01-fe63-4d5f-8544-e5b4d66439f5"]},"ActionDefinitionIds":["pendingcancellation_to_cancelled"]},{"$type":"Skyline.DataMiner.Net.Apps.DataMinerObjectModel.Buttons.DomInstanceButtonDefinition, SLNetTypes","Id":"pending_to_assesscancellation","Layout":{"Text":"Request Cancellation","Icon":"","ToolTip":"","Order":0},"VisibilityCondition":{"$type":"Skyline.DataMiner.Net.Apps.DataMinerObjectModel.Conditions.StatusCondition, SLNetTypes","Statuses":["23f9fa75-32b8-4e4a-bd65-06a7344d1902"]},"ActionDefinitionIds":["pending_to_assesscancellation"]},{"$type":"Skyline.DataMiner.Net.Apps.DataMinerObjectModel.Buttons.DomInstanceButtonDefinition, SLNetTypes","Id":"held_to_inprogress","Layout":{"Text":"Issue Resolved","Icon":"","ToolTip":"","Order":0},"VisibilityCondition":{"$type":"Skyline.DataMiner.Net.Apps.DataMinerObjectModel.Conditions.StatusCondition, SLNetTypes","Statuses":["310ea9e9-f65c-4e11-8b1b-e2c34688ef44"]},"ActionDefinitionIds":["held_to_inprogress"]},{"$type":"Skyline.DataMiner.Net.Apps.DataMinerObjectModel.Buttons.DomInstanceButtonDefinition, SLNetTypes","Id":"pending_to_inprogress","Layout":{"Text":"Information Provided","Icon":"","ToolTip":"","Order":0},"VisibilityCondition":{"$type":"Skyline.DataMiner.Net.Apps.DataMinerObjectModel.Conditions.StatusCondition, SLNetTypes","Statuses":["23f9fa75-32b8-4e4a-bd65-06a7344d1902"]},"ActionDefinitionIds":["pending_to_inprogress"]},{"$type":"Skyline.DataMiner.Net.Apps.DataMinerObjectModel.Buttons.DomInstanceButtonDefinition, SLNetTypes","Id":"assesscancellation_to_pendingcancellation","Layout":{"Text":"Confirm Cancellation","Icon":"","ToolTip":"","Order":1},"VisibilityCondition":{"$type":"Skyline.DataMiner.Net.Apps.DataMinerObjectModel.Conditions.StatusCondition, SLNetTypes","Statuses":["f7e93ddd-cddf-4755-a3e5-0f6ff885dcf5"]},"ActionDefinitionIds":["assesscancellation_to_pendingcancellation"]}],"ActionDefinitions":[{"$type":"Skyline.DataMiner.Net.Apps.DataMinerObjectModel.Actions.ExecuteScriptDomActionDefinition, SLNetTypes","Id":"new_to_acknowledged","Condition":{"$type":"Skyline.DataMiner.Net.Apps.DataMinerObjectModel.Conditions.StatusCondition, SLNetTypes","Statuses":["06df5562-cd9b-4b0b-bd45-c58560a8b22a"]},"Script":"ServiceOrder_StateTranstitions","Async":false,"IsInteractive":false,"ScriptOptions":["PARAMETERBYNAME:PreviousState:new","PARAMETERBYNAME:NextState:acknowledged"]},{"$type":"Skyline.DataMiner.Net.Apps.DataMinerObjectModel.Actions.ExecuteScriptDomActionDefinition, SLNetTypes","Id":"acknowledged_to_inprogress","Condition":{"$type":"Skyline.DataMiner.Net.Apps.DataMinerObjectModel.Conditions.StatusCondition, SLNetTypes","Statuses":["d917fc53-2638-4ab9-9ac6-651ec5312bac","06df5562-cd9b-4b0b-bd45-c58560a8b22a"]},"Script":"ServiceOrder_StateTranstitions","Async":false,"IsInteractive":false,"ScriptOptions":["PARAMETERBYNAME:PreviousState:acknowledged","PARAMETERBYNAME:NextState:inprogress"]},{"$type":"Skyline.DataMiner.Net.Apps.DataMinerObjectModel.Actions.ExecuteScriptDomActionDefinition, SLNetTypes","Id":"inprogress_to_completed","Condition":{"$type":"Skyline.DataMiner.Net.Apps.DataMinerObjectModel.Conditions.StatusCondition, SLNetTypes","Statuses":["331dc1c2-1950-4c00-a4ae-0aba674a30e6"]},"Script":"ServiceOrder_StateTranstitions","Async":false,"IsInteractive":false,"ScriptOptions":["PARAMETERBYNAME:PreviousState:inprogress","PARAMETERBYNAME:NextState:completed"]},{"$type":"Skyline.DataMiner.Net.Apps.DataMinerObjectModel.Actions.ExecuteScriptDomActionDefinition, SLNetTypes","Id":"new_to_rejected","Condition":{"$type":"Skyline.DataMiner.Net.Apps.DataMinerObjectModel.Conditions.StatusCondition, SLNetTypes","Statuses":["06df5562-cd9b-4b0b-bd45-c58560a8b22a"]},"Script":"ServiceOrder_StateTranstitions","Async":false,"IsInteractive":false,"ScriptOptions":["PARAMETERBYNAME:PreviousState:new","PARAMETERBYNAME:NextState:rejected"]},{"$type":"Skyline.DataMiner.Net.Apps.DataMinerObjectModel.Actions.ExecuteScriptDomActionDefinition, SLNetTypes","Id":"acknowledged_to_rejected","Condition":{"$type":"Skyline.DataMiner.Net.Apps.DataMinerObjectModel.Conditions.StatusCondition, SLNetTypes","Statuses":["d917fc53-2638-4ab9-9ac6-651ec5312bac"]},"Script":"ServiceOrder_StateTranstitions","Async":false,"IsInteractive":false,"ScriptOptions":["PARAMETERBYNAME:PreviousState:acknowledged","PARAMETERBYNAME:NextState:rejected"]},{"$type":"Skyline.DataMiner.Net.Apps.DataMinerObjectModel.Actions.ExecuteScriptDomActionDefinition, SLNetTypes","Id":"inprogess_to_failed","Condition":{"$type":"Skyline.DataMiner.Net.Apps.DataMinerObjectModel.Conditions.StatusCondition, SLNetTypes","Statuses":["331dc1c2-1950-4c00-a4ae-0aba674a30e6"]},"Script":"ServiceOrder_StateTranstitions","Async":false,"IsInteractive":false,"ScriptOptions":["PARAMETERBYNAME:PreviousState:inprogress","PARAMETERBYNAME:NextState:failed"]},{"$type":"Skyline.DataMiner.Net.Apps.DataMinerObjectModel.Actions.ExecuteScriptDomActionDefinition, SLNetTypes","Id":"inprogress_to_partial","Condition":{"$type":"Skyline.DataMiner.Net.Apps.DataMinerObjectModel.Conditions.StatusCondition, SLNetTypes","Statuses":["331dc1c2-1950-4c00-a4ae-0aba674a30e6"]},"Script":"ServiceOrder_StateTranstitions","Async":false,"IsInteractive":false,"ScriptOptions":["PARAMETERBYNAME:PreviousState:inprogress","PARAMETERBYNAME:NextState:partial"]},{"$type":"Skyline.DataMiner.Net.Apps.DataMinerObjectModel.Actions.ExecuteScriptDomActionDefinition, SLNetTypes","Id":"inprogress_to_held","Condition":{"$type":"Skyline.DataMiner.Net.Apps.DataMinerObjectModel.Conditions.StatusCondition, SLNetTypes","Statuses":["331dc1c2-1950-4c00-a4ae-0aba674a30e6"]},"Script":"ServiceOrder_StateTranstitions","Async":false,"IsInteractive":false,"ScriptOptions":["PARAMETERBYNAME:PreviousState:inprogress","PARAMETERBYNAME:NextState:held"]},{"$type":"Skyline.DataMiner.Net.Apps.DataMinerObjectModel.Actions.ExecuteScriptDomActionDefinition, SLNetTypes","Id":"inprogress_to_pending","Condition":{"$type":"Skyline.DataMiner.Net.Apps.DataMinerObjectModel.Conditions.StatusCondition, SLNetTypes","Statuses":["331dc1c2-1950-4c00-a4ae-0aba674a30e6"]},"Script":"ServiceOrder_StateTranstitions","Async":false,"IsInteractive":false,"ScriptOptions":["PARAMETERBYNAME:PreviousState:new","PARAMETERBYNAME:NextState:acknowledged"]},{"$type":"Skyline.DataMiner.Net.Apps.DataMinerObjectModel.Actions.ExecuteScriptDomActionDefinition, SLNetTypes","Id":"held_to_assesscancellation","Condition":{"$type":"Skyline.DataMiner.Net.Apps.DataMinerObjectModel.Conditions.StatusCondition, SLNetTypes","Statuses":["310ea9e9-f65c-4e11-8b1b-e2c34688ef44"]},"Script":"ServiceOrder_StateTranstitions","Async":false,"IsInteractive":false,"ScriptOptions":["PARAMETERBYNAME:PreviousState:held","PARAMETERBYNAME:NextState:assesscancellation"]},{"$type":"Skyline.DataMiner.Net.Apps.DataMinerObjectModel.Actions.ExecuteScriptDomActionDefinition, SLNetTypes","Id":"assesscancellation_to_pendingcancellation","Condition":{"$type":"Skyline.DataMiner.Net.Apps.DataMinerObjectModel.Conditions.StatusCondition, SLNetTypes","Statuses":["f7e93ddd-cddf-4755-a3e5-0f6ff885dcf5"]},"Script":"ServiceOrder_StateTranstitions","Async":false,"IsInteractive":false,"ScriptOptions":["PARAMETERBYNAME:PreviousState:assesscancellation","PARAMETERBYNAME:NextState:pendingcancellation"]},{"$type":"Skyline.DataMiner.Net.Apps.DataMinerObjectModel.Actions.ExecuteScriptDomActionDefinition, SLNetTypes","Id":"pendingcancellation_to_cancelled","Condition":{"$type":"Skyline.DataMiner.Net.Apps.DataMinerObjectModel.Conditions.StatusCondition, SLNetTypes","Statuses":["15d08c01-fe63-4d5f-8544-e5b4d66439f5"]},"Script":"ServiceOrder_StateTranstitions","Async":false,"IsInteractive":false,"ScriptOptions":["PARAMETERBYNAME:PreviousState:pendingcancellation","PARAMETERBYNAME:NextState:cancelled"]},{"$type":"Skyline.DataMiner.Net.Apps.DataMinerObjectModel.Actions.ExecuteScriptDomActionDefinition, SLNetTypes","Id":"pending_to_assesscancellation","Condition":{"$type":"Skyline.DataMiner.Net.Apps.DataMinerObjectModel.Conditions.StatusCondition, SLNetTypes","Statuses":["23f9fa75-32b8-4e4a-bd65-06a7344d1902"]},"Script":"ServiceOrder_StateTranstitions","Async":false,"IsInteractive":false,"ScriptOptions":["PARAMETERBYNAME:PreviousState:pending","PARAMETERBYNAME:NextState:assesscancellation"]},{"$type":"Skyline.DataMiner.Net.Apps.DataMinerObjectModel.Actions.ExecuteScriptDomActionDefinition, SLNetTypes","Id":"held_to_inprogress","Condition":{"$type":"Skyline.DataMiner.Net.Apps.DataMinerObjectModel.Conditions.StatusCondition, SLNetTypes","Statuses":["310ea9e9-f65c-4e11-8b1b-e2c34688ef44"]},"Script":"ServiceOrder_StateTranstitions","Async":false,"IsInteractive":false,"ScriptOptions":["PARAMETERBYNAME:PreviousState:held","PARAMETERBYNAME:NextState:inprogress"]},{"$type":"Skyline.DataMiner.Net.Apps.DataMinerObjectModel.Actions.ExecuteScriptDomActionDefinition, SLNetTypes","Id":"pending_to_inprogress","Condition":{"$type":"Skyline.DataMiner.Net.Apps.DataMinerObjectModel.Conditions.StatusCondition, SLNetTypes","Statuses":["23f9fa75-32b8-4e4a-bd65-06a7344d1902"]},"Script":"ServiceOrder_StateTranstitions","Async":false,"IsInteractive":false,"ScriptOptions":["PARAMETERBYNAME:PreviousState:pending","PARAMETERBYNAME:NextState:inprogress"]}],"SyncLastModified":"2025-05-26T12:11:48.3869943Z","LastModifiedBy":"Admin","CreatedAt":"2025-05-26T12:11:48.3869943Z","CreatedBy":"Admin"}